finstar/__init__.py
finstar/evaluation/__init__.py
finstar/evaluation/returns.py
finstar/strategies/__init__.py
finstar/strategies/sma.py
finstar-0.2.0.dist-info/LICENSE
finstar-0.2.0.dist-info/WHEEL
finstar-0.2.0.dist-info/METADATA
finstar-0.2.0.dist-info/RECORD
